aioburst/__init__.py
aioburst/alimiter.py
aioburst-0.2.0.dist-info/LICENSE
aioburst-0.2.0.dist-info/WHEEL
aioburst-0.2.0.dist-info/METADATA
aioburst-0.2.0.dist-info/RECORD
