Metadata-Version: 2.1
Name: aioburst
Version: 0.2.0
Summary: A library to optimize the speed of rate limited async calls.
Author: ericfeunekes
Author-email: ericwill.f@gmail.com
Requires-Python: >=3.8,<4.0
Classifier: Programming Language :: Python :: 3
Classifier: Programming Language :: Python :: 3.8
Classifier: Programming Language :: Python :: 3.9
Classifier: Programming Language :: Python :: 3.10
Classifier: Programming Language :: Python :: 3.11
Requires-Dist: pendulum (>=2.1.2,<3.0.0)
Requires-Dist: pydantic (>=1.10.2,<2.0.0)
